<?xml version = '1.0' encoding = 'UTF-8'?>
<Relation class="oracle.dbtools.crest.model.design.logical.Relation" name="Proveedores/Libros Libro FK" directorySegmentName="seg_0" id="14A85393-6F36-B57C-5667-9DF557AD239E">
<createdBy>davef</createdBy>
<createdTime>2019-02-28 02:18:38 UTC</createdTime>
<ownerDesignName>LibreriaModeloLogico</ownerDesignName>
<engineerTo>
<item key="52CC9098-CB3F-D7EF-E200-B37E7EFED40C" value="true"/>
</engineerTo>
<sourcePk>D284F9F8-CCA4-0140-FC98-6C560B8473DF</sourcePk>
<identifying>false</identifying>
<optionalSource>true</optionalSource>
<optionalTarget>false</optionalTarget>
<sourceCardinality>1</sourceCardinality>
<sourceEntity>61E988A4-6DFF-8001-0B6D-52166737BE59</sourceEntity>
<targetCardinalityString>*</targetCardinalityString>
<targetEntity>26C73330-F815-79EB-ED51-1408D600FBB6</targetEntity>
<transferable>true</transferable>
<deleteRule>NO ACTION</deleteRule>
</Relation>